{
    "name_plates": [
        "../../idolmaster/image_sp/ui/refresh_room/name_plate/14.png",
        "../../idolmaster/image_sp/ui/refresh_room/name_plate/15.png",
        "../../idolmaster/image_sp/ui/refresh_room/name_plate/57.png",
        "../../idolmaster/image_sp/ui/refresh_room/name_plate/105.png"
    ],
    "name_plates_class": null,
    "data": {
        "id": "127",
        "refresh_room_id": "127",
        "start_time": "2019/12/25 15:00:00",
        "refresh_room_name": "クリスマス当日！<BR>プレゼントは何だろな～♪",
        "idol_set_id_1": "176",
        "idol_accessory_set_id_1": "122",
        "idol_set_id_2": "63",
        "idol_accessory_set_id_2": "123",
        "idol_set_id_3": "133",
        "idol_accessory_set_id_3": "124",
        "idol_set_id_4": "151",
        "idol_accessory_set_id_4": "125",
        "idol_set_id_5": "",
        "idol_accessory_set_id_5": "",
        "idol_name_1": "柳瀬美由紀",
        "idol_kana_1": "やなせみゆき",
        "name_plate_id_1": "14",
        "idol_name_2": "櫻井桃華",
        "idol_kana_2": "さくらいももか",
        "name_plate_id_2": "15",
        "idol_name_3": "古賀小春",
        "idol_kana_3": "こがこはる",
        "name_plate_id_3": "57",
        "idol_name_4": "佐城雪美",
        "idol_kana_4": "さじょうゆきみ",
        "name_plate_id_4": "105",
        "idol_name_5": "",
        "idol_kana_5": "",
        "idol_avatar": {
            "1": {
                "attribute": "1",
                "body_type": "2",
                "breast_size": "3",
                "short_name": "美由紀",
                "image_url_list": {
                    "expression_1177": "../../idolmaster/js/petit_cg/expression/1177.js",
                    "hair_10177": "../../idolmaster/js/petit_cg/hair/10177.js",
                    "costume_2_23458": "../../idolmaster/js/petit_cg/costume/2/23458.js",
                    "head_2_33213": "../../idolmaster/js/petit_cg/head/2/33213.js"
                },
                "sub_type_list": {
                    "head": null,
                    "hand": null,
                    "leg": null
                },
                "take_sub_type": {
                    "head": 0,
                    "hand": 0,
                    "leg": 0
                },
                "petit_csv_info_list": {
                    "costume_2_23458": {
                        "image_path": "../../idolmaster/image_sp/item/l/petit_cg/23458.png",
                        "accessory_name": "ふわキュン♪サンタ",
                        "explanation": "雪の結晶を散りばめた、ふわふわキュートなサンタ衣装です。<br>可愛いサンタが、キュンキュンのプレゼントをお届けです♪",
                        "type_id": "2"
                    },
                    "head_2_33213": {
                        "image_path": "../../idolmaster/image_sp/item/l/petit_cg/33213.png",
                        "accessory_name": "ふわキュン♪リボン",
                        "explanation": "華やかにビジューでデコった、大きなリボンカチューシャです。<br>サンタだって、可愛いのが好き♪",
                        "type_id": "3"
                    }
                },
                "petit_csv_sub_type_info_list": []
            },
            "2": {
                "attribute": "1",
                "body_type": "2",
                "breast_size": "3",
                "short_name": "桃華",
                "image_url_list": {
                    "expression_1034": "../../idolmaster/js/petit_cg/expression/1034.js",
                    "hair_10034": "../../idolmaster/js/petit_cg/hair/10034.js",
                    "costume_2_23054": "../../idolmaster/js/petit_cg/costume/2/23054.js",
                    "head_2_33056": "../../idolmaster/js/petit_cg/head/2/33056.js"
                },
                "sub_type_list": {
                    "head": null,
                    "hand": null,
                    "leg": null
                },
                "take_sub_type": {
                    "head": 0,
                    "hand": 0,
                    "leg": 0
                },
                "petit_csv_info_list": {
                    "costume_2_23054": {
                        "image_path": "../../idolmaster/image_sp/item/l/petit_cg/23054.png",
                        "accessory_name": "赤ずきんワンピ",
                        "explanation": "おとぎ話の赤ずきんをイメージした衣装です。<br>かわいく身支度して会いにいきましょ♪",
                        "type_id": "2"
                    },
                    "head_2_33056": {
                        "image_path": "../../idolmaster/image_sp/item/l/petit_cg/33056.png",
                        "accessory_name": "メリクリサンタ帽",
                        "explanation": "トナカイの角がついたサンタ帽です。<br>聖夜に幸せをお届け!",
                        "type_id": "3"
                    }
                },
                "petit_csv_sub_type_info_list": []
            },
            "3": {
                "attribute": "1",
                "body_type": "2",
                "breast_size": "3",
                "short_name": "小春",
                "image_url_list": {
                    "expression_1143": "../../idolmaster/js/petit_cg/expression/1143.js",
                    "hair_10143": "../../idolmaster/js/petit_cg/hair/10143.js",
                    "costume_2_23223": "../../idolmaster/js/petit_cg/costume/2/23223.js",
                    "head_2_33088": "../../idolmaster/js/petit_cg/head/2/33088.js",
                    "hand_2_42020": "../../idolmaster/js/petit_cg/hand/2/42020.js",
                    "leg_2_51045": "../../idolmaster/js/petit_cg/leg/2/51045.js"
                },
                "sub_type_list": {
                    "head": null,
                    "hand": null,
                    "leg": null
                },
                "take_sub_type": {
                    "head": 0,
                    "hand": 0,
                    "leg": 0
                },
                "petit_csv_info_list": {
                    "costume_2_23223": {
                        "image_path": "../../idolmaster/image_sp/item/l/petit_cg/23223.png",
                        "accessory_name": "メニーメリーツリー",
                        "explanation": "クリスマスツリーがモチーフの衣装です。<br>プレゼントはまだかな～?",
                        "type_id": "2"
                    },
                    "head_2_33088": {
                        "image_path": "../../idolmaster/image_sp/item/l/petit_cg/33088.png",
                        "accessory_name": "メニーメリーツリーハット",
                        "explanation": "クリスマスツリーがモチーフの帽子です。<br>輝く星とクマちゃんがキュート☆",
                        "type_id": "3"
                    },
                    "hand_2_42020": {
                        "image_path": "../../idolmaster/image_sp/item/l/petit_cg/42020.png",
                        "accessory_name": "ベリーベリーケーキブレス",
                        "explanation": "つやつやイチゴがかわいいブレスレットです。<br>一粒食べたら、たちまち幸せ!",
                        "type_id": "4"
                    },
                    "leg_2_51045": {
                        "image_path": "../../idolmaster/image_sp/item/l/petit_cg/51045.png",
                        "accessory_name": "メニーメリーツリーカバー",
                        "explanation": "オーナメントがついたグリーンのアームカバーです。<br>あったか足元で、クリスマスを楽しもう!",
                        "type_id": "5"
                    }
                },
                "petit_csv_sub_type_info_list": []
            },
            "4": {
                "attribute": "2",
                "body_type": "2",
                "breast_size": "3",
                "short_name": "雪美",
                "image_url_list": {
                    "expression_1115": "../../idolmaster/js/petit_cg/expression/1115.js",
                    "hair_10115": "../../idolmaster/js/petit_cg/hair/10115.js",
                    "costume_2_23306": "../../idolmaster/js/petit_cg/costume/2/23306.js",
                    "head_2_33133": "../../idolmaster/js/petit_cg/head/2/33133.js"
                },
                "sub_type_list": {
                    "head": null,
                    "hand": null,
                    "leg": null
                },
                "take_sub_type": {
                    "head": 0,
                    "hand": 0,
                    "leg": 0
                },
                "petit_csv_info_list": {
                    "costume_2_23306": {
                        "image_path": "../../idolmaster/image_sp/item/l/petit_cg/23306.png",
                        "accessory_name": "ハピクリ☆ショーパンサンタ",
                        "explanation": "活発なショートパンツタイプのサンタ衣装です。<br>元気いっぱい、聖夜を駆け回っちゃおう!",
                        "type_id": "2"
                    },
                    "head_2_33133": {
                        "image_path": "../../idolmaster/image_sp/item/l/petit_cg/33133.png",
                        "accessory_name": "ハピクリ☆ネコ耳サンタ帽",
                        "explanation": "ふわふわのネコ耳付きサンタ帽です。<br>にゃんともキュートな可愛さで、幸せをお届け♪",
                        "type_id": "3"
                    }
                },
                "petit_csv_sub_type_info_list": []
            }
        }
    },
    "detail": [
        {
            "id": "1",
            "refresh_room_id": "127",
            "idol_disp_1": "",
            "idol_disp_2": "",
            "idol_disp_3": "",
            "idol_disp_4": "",
            "idol_disp_5": "",
            "motion1": "joy",
            "motion2": "out",
            "motion3": "out",
            "motion4": "out",
            "motion5": "",
            "bg_image": "6",
            "message": "わあ～っ！　すごいすごーいっ！\nみんな、来て来てーっ！",
            "message_window_type": "",
            "message_arrow_1": "1",
            "message_arrow_2": "",
            "message_arrow_3": "",
            "message_arrow_4": "",
            "message_arrow_5": ""
        },
        {
            "id": "2",
            "refresh_room_id": "127",
            "idol_disp_1": "",
            "idol_disp_2": "",
            "idol_disp_3": "",
            "idol_disp_4": "",
            "idol_disp_5": "",
            "motion1": "",
            "motion2": "in_walk",
            "motion3": "in_walk",
            "motion4": "in_walk",
            "motion5": "",
            "bg_image": "",
            "message": "わあ……プレゼント……\nたくさん……。",
            "message_window_type": "",
            "message_arrow_1": "",
            "message_arrow_2": "",
            "message_arrow_3": "",
            "message_arrow_4": "1",
            "message_arrow_5": ""
        },
        {
            "id": "3",
            "refresh_room_id": "127",
            "idol_disp_1": "",
            "idol_disp_2": "",
            "idol_disp_3": "",
            "idol_disp_4": "",
            "idol_disp_5": "",
            "motion1": "",
            "motion2": "question_left",
            "motion3": "",
            "motion4": "",
            "motion5": "",
            "bg_image": "",
            "message": "昨日はありませんでしたわよね？\n一体どなたが…？",
            "message_window_type": "",
            "message_arrow_1": "",
            "message_arrow_2": "1",
            "message_arrow_3": "",
            "message_arrow_4": "",
            "message_arrow_5": ""
        },
        {
            "id": "4",
            "refresh_room_id": "127",
            "idol_disp_1": "",
            "idol_disp_2": "",
            "idol_disp_3": "",
            "idol_disp_4": "",
            "idol_disp_5": "",
            "motion1": "",
            "motion2": "",
            "motion3": "smile_left",
            "motion4": "",
            "motion5": "",
            "bg_image": "",
            "message": "サンタさんですよ～♪\n今日はクリスマスですから～。",
            "message_window_type": "",
            "message_arrow_1": "",
            "message_arrow_2": "",
            "message_arrow_3": "1",
            "message_arrow_4": "",
            "message_arrow_5": ""
        },
        {
            "id": "5",
            "refresh_room_id": "127",
            "idol_disp_1": "",
            "idol_disp_2": "",
            "idol_disp_3": "",
            "idol_disp_4": "",
            "idol_disp_5": "",
            "motion1": "nod_smile",
            "motion2": "",
            "motion3": "",
            "motion4": "",
            "motion5": "",
            "bg_image": "",
            "message": "サンタさん、来てたんだー！\nもうちょっとでクリスマス会が\n始まるのに、帰っちゃったのかなぁ？",
            "message_window_type": "",
            "message_arrow_1": "1",
            "message_arrow_2": "",
            "message_arrow_3": "",
            "message_arrow_4": "",
            "message_arrow_5": ""
        },
        {
            "id": "6",
            "refresh_room_id": "127",
            "idol_disp_1": "",
            "idol_disp_2": "",
            "idol_disp_3": "",
            "idol_disp_4": "",
            "idol_disp_5": "",
            "motion1": "",
            "motion2": "trouble",
            "motion3": "",
            "motion4": "",
            "motion5": "",
            "bg_image": "",
            "message": "きっとお忙しい方なのでしょうね。\nせっかく素敵な会がありますのに、\nご一緒できず残念ですわ…。",
            "message_window_type": "",
            "message_arrow_1": "",
            "message_arrow_2": "1",
            "message_arrow_3": "",
            "message_arrow_4": "",
            "message_arrow_5": ""
        },
        {
            "id": "7",
            "refresh_room_id": "127",
            "idol_disp_1": "",
            "idol_disp_2": "",
            "idol_disp_3": "",
            "idol_disp_4": "",
            "idol_disp_5": "",
            "motion1": "",
            "motion2": "",
            "motion3": "notice",
            "motion4": "",
            "motion5": "",
            "bg_image": "",
            "message": "あれ～？　みなさん、\n見てください～。プレゼントに\n何か書いてありませんか～？",
            "message_window_type": "",
            "message_arrow_1": "",
            "message_arrow_2": "",
            "message_arrow_3": "1",
            "message_arrow_4": "",
            "message_arrow_5": ""
        },
        {
            "id": "8",
            "refresh_room_id": "127",
            "idol_disp_1": "",
            "idol_disp_2": "",
            "idol_disp_3": "",
            "idol_disp_4": "",
            "idol_disp_5": "",
            "motion1": "",
            "motion2": "",
            "motion3": "nod_smile",
            "motion4": "",
            "motion5": "",
            "bg_image": "",
            "message": "『ペロちゃん&ヒョウくんへ』\nヒョウくんたち宛ての\nプレゼントみたいです～♪",
            "message_window_type": "",
            "message_arrow_1": "",
            "message_arrow_2": "",
            "message_arrow_3": "1",
            "message_arrow_4": "",
            "message_arrow_5": ""
        },
        {
            "id": "9",
            "refresh_room_id": "127",
            "idol_disp_1": "",
            "idol_disp_2": "",
            "idol_disp_3": "",
            "idol_disp_4": "",
            "idol_disp_5": "",
            "motion1": "",
            "motion2": "",
            "motion3": "",
            "motion4": "smile_left",
            "motion5": "",
            "bg_image": "",
            "message": "ほんとだ……。嬉しい……\nペロも、きっと喜ぶ……。",
            "message_window_type": "",
            "message_arrow_1": "",
            "message_arrow_2": "",
            "message_arrow_3": "",
            "message_arrow_4": "1",
            "message_arrow_5": ""
        },
        {
            "id": "10",
            "refresh_room_id": "127",
            "idol_disp_1": "",
            "idol_disp_2": "",
            "idol_disp_3": "",
            "idol_disp_4": "",
            "idol_disp_5": "",
            "motion1": "shock",
            "motion2": "",
            "motion3": "",
            "motion4": "",
            "motion5": "",
            "bg_image": "",
            "message": "あーっ！　他のプレゼントにも、\n何か書いてあるよ！",
            "message_window_type": "",
            "message_arrow_1": "1",
            "message_arrow_2": "",
            "message_arrow_3": "",
            "message_arrow_4": "",
            "message_arrow_5": ""
        },
        {
            "id": "11",
            "refresh_room_id": "127",
            "idol_disp_1": "",
            "idol_disp_2": "",
            "idol_disp_3": "",
            "idol_disp_4": "",
            "idol_disp_5": "",
            "motion1": "",
            "motion2": "light_joy",
            "motion3": "",
            "motion4": "",
            "motion5": "",
            "bg_image": "",
            "message": "『よいこのみんなへ』\n…これは、わたくしたち宛てと\n思ってよいのかしら。",
            "message_window_type": "",
            "message_arrow_1": "",
            "message_arrow_2": "1",
            "message_arrow_3": "",
            "message_arrow_4": "",
            "message_arrow_5": ""
        },
        {
            "id": "12",
            "refresh_room_id": "127",
            "idol_disp_1": "",
            "idol_disp_2": "",
            "idol_disp_3": "",
            "idol_disp_4": "",
            "idol_disp_5": "",
            "motion1": "",
            "motion2": "",
            "motion3": "smile_left",
            "motion4": "",
            "motion5": "",
            "bg_image": "",
            "message": "きっと、そうですよ～♪\n小春たちへのプレゼントです～。",
            "message_window_type": "",
            "message_arrow_1": "",
            "message_arrow_2": "",
            "message_arrow_3": "1",
            "message_arrow_4": "",
            "message_arrow_5": ""
        },
        {
            "id": "13",
            "refresh_room_id": "127",
            "idol_disp_1": "",
            "idol_disp_2": "",
            "idol_disp_3": "",
            "idol_disp_4": "",
            "idol_disp_5": "",
            "motion1": "smile_right",
            "motion2": "",
            "motion3": "",
            "motion4": "",
            "motion5": "",
            "bg_image": "",
            "message": "やったー♪\n何が入ってるんだろー？",
            "message_window_type": "",
            "message_arrow_1": "1",
            "message_arrow_2": "",
            "message_arrow_3": "",
            "message_arrow_4": "",
            "message_arrow_5": ""
        },
        {
            "id": "14",
            "refresh_room_id": "127",
            "idol_disp_1": "",
            "idol_disp_2": "",
            "idol_disp_3": "",
            "idol_disp_4": "",
            "idol_disp_5": "",
            "motion1": "",
            "motion2": "",
            "motion3": "nod_smile",
            "motion4": "",
            "motion5": "",
            "bg_image": "",
            "message": "メッセージカードがありますよ～。\n『新しいおともだちです。\n仲良くしてあげてくださいね♪』",
            "message_window_type": "",
            "message_arrow_1": "",
            "message_arrow_2": "",
            "message_arrow_3": "1",
            "message_arrow_4": "",
            "message_arrow_5": ""
        },
        {
            "id": "15",
            "refresh_room_id": "127",
            "idol_disp_1": "",
            "idol_disp_2": "",
            "idol_disp_3": "",
            "idol_disp_4": "",
            "idol_disp_5": "",
            "motion1": "",
            "motion2": "",
            "motion3": "",
            "motion4": "nod",
            "motion5": "",
            "bg_image": "",
            "message": "友だち…………猫……？\nでも……にゃあ、って……\n聞こえない……。",
            "message_window_type": "",
            "message_arrow_1": "",
            "message_arrow_2": "",
            "message_arrow_3": "",
            "message_arrow_4": "1",
            "message_arrow_5": ""
        },
        {
            "id": "16",
            "refresh_room_id": "127",
            "idol_disp_1": "",
            "idol_disp_2": "",
            "idol_disp_3": "",
            "idol_disp_4": "",
            "idol_disp_5": "",
            "motion1": "shy",
            "motion2": "",
            "motion3": "",
            "motion4": "",
            "motion5": "",
            "bg_image": "",
            "message": "さすがに猫さんは\n入ってないんじゃないかな～？\nガタガタ動いたりもしてないし。",
            "message_window_type": "",
            "message_arrow_1": "1",
            "message_arrow_2": "",
            "message_arrow_3": "",
            "message_arrow_4": "",
            "message_arrow_5": ""
        },
        {
            "id": "17",
            "refresh_room_id": "127",
            "idol_disp_1": "",
            "idol_disp_2": "",
            "idol_disp_3": "",
            "idol_disp_4": "",
            "idol_disp_5": "",
            "motion1": "",
            "motion2": "",
            "motion3": "",
            "motion4": "notice",
            "motion5": "",
            "bg_image": "",
            "message": "じゃあ………\n猫の、ぬいぐるみ……とか？",
            "message_window_type": "",
            "message_arrow_1": "",
            "message_arrow_2": "",
            "message_arrow_3": "",
            "message_arrow_4": "1",
            "message_arrow_5": ""
        },
        {
            "id": "18",
            "refresh_room_id": "127",
            "idol_disp_1": "",
            "idol_disp_2": "",
            "idol_disp_3": "",
            "idol_disp_4": "",
            "idol_disp_5": "",
            "motion1": "",
            "motion2": "smile_right",
            "motion3": "",
            "motion4": "",
            "motion5": "",
            "bg_image": "",
            "message": "まぁ、ぬいぐるみ！\n気になりますわね♪",
            "message_window_type": "",
            "message_arrow_1": "",
            "message_arrow_2": "1",
            "message_arrow_3": "",
            "message_arrow_4": "",
            "message_arrow_5": ""
        },
        {
            "id": "19",
            "refresh_room_id": "127",
            "idol_disp_1": "",
            "idol_disp_2": "",
            "idol_disp_3": "",
            "idol_disp_4": "",
            "idol_disp_5": "",
            "motion1": "",
            "motion2": "",
            "motion3": "light_joy",
            "motion4": "",
            "motion5": "",
            "bg_image": "",
            "message": "ぬいぐるみ、可愛いですよね～。\n小春も大好きです～♪",
            "message_window_type": "",
            "message_arrow_1": "",
            "message_arrow_2": "",
            "message_arrow_3": "1",
            "message_arrow_4": "",
            "message_arrow_5": ""
        },
        {
            "id": "20",
            "refresh_room_id": "127",
            "idol_disp_1": "",
            "idol_disp_2": "",
            "idol_disp_3": "",
            "idol_disp_4": "",
            "idol_disp_5": "",
            "motion1": "",
            "motion2": "",
            "motion3": "",
            "motion4": "shy",
            "motion5": "",
            "bg_image": "",
            "message": "ふかふか……ふわふわ……。\nナデナデ……気持ちいい。\n私も……好き。",
            "message_window_type": "",
            "message_arrow_1": "",
            "message_arrow_2": "",
            "message_arrow_3": "",
            "message_arrow_4": "1",
            "message_arrow_5": ""
        },
        {
            "id": "21",
            "refresh_room_id": "127",
            "idol_disp_1": "",
            "idol_disp_2": "",
            "idol_disp_3": "",
            "idol_disp_4": "",
            "idol_disp_5": "",
            "motion1": "",
            "motion2": "joy",
            "motion3": "",
            "motion4": "",
            "motion5": "",
            "bg_image": "",
            "message": "ふふっ、わたくしもですわ。\nレディも、普段はただの女の子。\n可愛いものは、好きですもの。",
            "message_window_type": "",
            "message_arrow_1": "",
            "message_arrow_2": "1",
            "message_arrow_3": "",
            "message_arrow_4": "",
            "message_arrow_5": ""
        },
        {
            "id": "22",
            "refresh_room_id": "127",
            "idol_disp_1": "",
            "idol_disp_2": "",
            "idol_disp_3": "",
            "idol_disp_4": "",
            "idol_disp_5": "",
            "motion1": "",
            "motion2": "",
            "motion3": "smile_left",
            "motion4": "",
            "motion5": "",
            "bg_image": "",
            "message": "あ、まだ続きがあるみたいです～。\n『名前は「はぴねす」「ぷりんす」\n「ぶらむす」「すちむす」だよ♪』",
            "message_window_type": "",
            "message_arrow_1": "",
            "message_arrow_2": "",
            "message_arrow_3": "1",
            "message_arrow_4": "",
            "message_arrow_5": ""
        },
        {
            "id": "23",
            "refresh_room_id": "127",
            "idol_disp_1": "",
            "idol_disp_2": "",
            "idol_disp_3": "",
            "idol_disp_4": "",
            "idol_disp_5": "",
            "motion1": "",
            "motion2": "nod",
            "motion3": "",
            "motion4": "",
            "motion5": "",
            "bg_image": "",
            "message": "「はぴねす」は、幸せという意味。\n「ぷりんす」は、王子様でしたわね。\n「ぶらむす」は…音楽家でしょうか？",
            "message_window_type": "",
            "message_arrow_1": "",
            "message_arrow_2": "1",
            "message_arrow_3": "",
            "message_arrow_4": "",
            "message_arrow_5": ""
        },
        {
            "id": "24",
            "refresh_room_id": "127",
            "idol_disp_1": "",
            "idol_disp_2": "",
            "idol_disp_3": "",
            "idol_disp_4": "",
            "idol_disp_5": "",
            "motion1": "smile_right",
            "motion2": "",
            "motion3": "",
            "motion4": "",
            "motion5": "",
            "bg_image": "",
            "message": "桃華ちゃん、すごーいっ！\nじゃあ、「すちむす」は？",
            "message_window_type": "",
            "message_arrow_1": "1",
            "message_arrow_2": "",
            "message_arrow_3": "",
            "message_arrow_4": "",
            "message_arrow_5": ""
        },
        {
            "id": "25",
            "refresh_room_id": "127",
            "idol_disp_1": "",
            "idol_disp_2": "",
            "idol_disp_3": "",
            "idol_disp_4": "",
            "idol_disp_5": "",
            "motion1": "",
            "motion2": "smile_left",
            "motion3": "",
            "motion4": "",
            "motion5": "",
            "bg_image": "",
            "message": "そうですわね……\nこの流れであれば、何かしらの\n英語のような気もしますけど……",
            "message_window_type": "",
            "message_arrow_1": "",
            "message_arrow_2": "1",
            "message_arrow_3": "",
            "message_arrow_4": "",
            "message_arrow_5": ""
        },
        {
            "id": "26",
            "refresh_room_id": "127",
            "idol_disp_1": "",
            "idol_disp_2": "",
            "idol_disp_3": "",
            "idol_disp_4": "",
            "idol_disp_5": "",
            "motion1": "",
            "motion2": "trouble",
            "motion3": "",
            "motion4": "",
            "motion5": "",
            "bg_image": "",
            "message": "ごめんなさい。\nわたくし、存じ上げなくて……。",
            "message_window_type": "",
            "message_arrow_1": "",
            "message_arrow_2": "1",
            "message_arrow_3": "",
            "message_arrow_4": "",
            "message_arrow_5": ""
        },
        {
            "id": "27",
            "refresh_room_id": "127",
            "idol_disp_1": "",
            "idol_disp_2": "",
            "idol_disp_3": "",
            "idol_disp_4": "",
            "idol_disp_5": "",
            "motion1": "",
            "motion2": "",
            "motion3": "",
            "motion4": "light_joy",
            "motion5": "",
            "bg_image": "",
            "message": "中……見れば……わかるかも。\n開けてみる……？",
            "message_window_type": "",
            "message_arrow_1": "",
            "message_arrow_2": "",
            "message_arrow_3": "",
            "message_arrow_4": "1",
            "message_arrow_5": ""
        },
        {
            "id": "28",
            "refresh_room_id": "127",
            "idol_disp_1": "",
            "idol_disp_2": "",
            "idol_disp_3": "",
            "idol_disp_4": "",
            "idol_disp_5": "",
            "motion1": "shout",
            "motion2": "",
            "motion3": "",
            "motion4": "",
            "motion5": "",
            "bg_image": "",
            "message": "じゃあじゃあ、ひとつだけ…\nちらっと！　じゃじゃーん！\n……おお～！",
            "message_window_type": "",
            "message_arrow_1": "1",
            "message_arrow_2": "",
            "message_arrow_3": "",
            "message_arrow_4": "",
            "message_arrow_5": ""
        },
        {
            "id": "29",
            "refresh_room_id": "127",
            "idol_disp_1": "",
            "idol_disp_2": "",
            "idol_disp_3": "",
            "idol_disp_4": "",
            "idol_disp_5": "",
            "motion1": "joy",
            "motion2": "joy",
            "motion3": "joy",
            "motion4": "joy",
            "motion5": "",
            "bg_image": "",
            "message": "可愛い……！",
            "message_window_type": "",
            "message_arrow_1": "1",
            "message_arrow_2": "1",
            "message_arrow_3": "1",
            "message_arrow_4": "1",
            "message_arrow_5": ""
        },
        {
            "id": "30",
            "refresh_room_id": "127",
            "idol_disp_1": "",
            "idol_disp_2": "",
            "idol_disp_3": "",
            "idol_disp_4": "",
            "idol_disp_5": "",
            "motion1": "",
            "motion2": "",
            "motion3": "smile_left",
            "motion4": "",
            "motion5": "",
            "bg_image": "",
            "message": "本当に、ぬいぐるみでしたね～。\n優しいお顔のウサギさんです～♪",
            "message_window_type": "",
            "message_arrow_1": "",
            "message_arrow_2": "",
            "message_arrow_3": "1",
            "message_arrow_4": "",
            "message_arrow_5": ""
        },
        {
            "id": "31",
            "refresh_room_id": "127",
            "idol_disp_1": "",
            "idol_disp_2": "",
            "idol_disp_3": "",
            "idol_disp_4": "",
            "idol_disp_5": "",
            "motion1": "",
            "motion2": "",
            "motion3": "",
            "motion4": "shy",
            "motion5": "",
            "bg_image": "",
            "message": "ふかふか、可愛い……♪\n他の箱の子も、見たい……。",
            "message_window_type": "",
            "message_arrow_1": "",
            "message_arrow_2": "",
            "message_arrow_3": "",
            "message_arrow_4": "1",
            "message_arrow_5": ""
        },
        {
            "id": "32",
            "refresh_room_id": "127",
            "idol_disp_1": "",
            "idol_disp_2": "",
            "idol_disp_3": "",
            "idol_disp_4": "",
            "idol_disp_5": "",
            "motion1": "",
            "motion2": "",
            "motion3": "notice",
            "motion4": "",
            "motion5": "",
            "bg_image": "",
            "message": "あ、待ってください雪美ちゃん～。\n残りは、クリスマス会が\n始まってから開けませんか～？",
            "message_window_type": "",
            "message_arrow_1": "",
            "message_arrow_2": "",
            "message_arrow_3": "1",
            "message_arrow_4": "",
            "message_arrow_5": ""
        },
        {
            "id": "33",
            "refresh_room_id": "127",
            "idol_disp_1": "",
            "idol_disp_2": "",
            "idol_disp_3": "",
            "idol_disp_4": "",
            "idol_disp_5": "",
            "motion1": "",
            "motion2": "",
            "motion3": "",
            "motion4": "light_joy",
            "motion5": "",
            "bg_image": "",
            "message": "みんなで、開ける……？\nそっか……楽しそう……。\nうん……そうしよう……。",
            "message_window_type": "",
            "message_arrow_1": "",
            "message_arrow_2": "",
            "message_arrow_3": "",
            "message_arrow_4": "1",
            "message_arrow_5": ""
        },
        {
            "id": "34",
            "refresh_room_id": "127",
            "idol_disp_1": "",
            "idol_disp_2": "",
            "idol_disp_3": "",
            "idol_disp_4": "",
            "idol_disp_5": "",
            "motion1": "smile_right",
            "motion2": "",
            "motion3": "",
            "motion4": "",
            "motion5": "",
            "bg_image": "",
            "message": "みゆきも、賛成ーっ！\nみんな、早く来ないかな～？",
            "message_window_type": "",
            "message_arrow_1": "1",
            "message_arrow_2": "",
            "message_arrow_3": "",
            "message_arrow_4": "",
            "message_arrow_5": ""
        },
        {
            "id": "35",
            "refresh_room_id": "127",
            "idol_disp_1": "",
            "idol_disp_2": "",
            "idol_disp_3": "",
            "idol_disp_4": "",
            "idol_disp_5": "",
            "motion1": "",
            "motion2": "",
            "motion3": "nod_smile",
            "motion4": "",
            "motion5": "",
            "bg_image": "",
            "message": "小春たち、はりきって\n早く来ちゃいましたもんね～。\n衣装も、バッチリです～♪",
            "message_window_type": "",
            "message_arrow_1": "",
            "message_arrow_2": "",
            "message_arrow_3": "1",
            "message_arrow_4": "",
            "message_arrow_5": ""
        },
        {
            "id": "36",
            "refresh_room_id": "127",
            "idol_disp_1": "",
            "idol_disp_2": "",
            "idol_disp_3": "",
            "idol_disp_4": "",
            "idol_disp_5": "",
            "motion1": "",
            "motion2": "smile_right",
            "motion3": "",
            "motion4": "",
            "motion5": "",
            "bg_image": "",
            "message": "みなさん、よくお似合いですわ♪\nクリスマス会に相応しい\n華やかな装いになりましたわね。",
            "message_window_type": "",
            "message_arrow_1": "",
            "message_arrow_2": "1",
            "message_arrow_3": "",
            "message_arrow_4": "",
            "message_arrow_5": ""
        },
        {
            "id": "37",
            "refresh_room_id": "127",
            "idol_disp_1": "",
            "idol_disp_2": "",
            "idol_disp_3": "",
            "idol_disp_4": "",
            "idol_disp_5": "",
            "motion1": "light_joy",
            "motion2": "",
            "motion3": "",
            "motion4": "",
            "motion5": "",
            "bg_image": "",
            "message": "早くみんなに見せたいなー！\nサンタさんにも、見せられたら\nもっとよかったのにねーっ。",
            "message_window_type": "",
            "message_arrow_1": "1",
            "message_arrow_2": "",
            "message_arrow_3": "",
            "message_arrow_4": "",
            "message_arrow_5": ""
        },
        {
            "id": "38",
            "refresh_room_id": "127",
            "idol_disp_1": "",
            "idol_disp_2": "",
            "idol_disp_3": "",
            "idol_disp_4": "",
            "idol_disp_5": "",
            "motion1": "",
            "motion2": "nod",
            "motion3": "",
            "motion4": "",
            "motion5": "",
            "bg_image": "",
            "message": "ええ、本当に。\nそれにやはり、素敵なプレゼントの\nお礼を直接お伝えしたいです。",
            "message_window_type": "",
            "message_arrow_1": "",
            "message_arrow_2": "1",
            "message_arrow_3": "",
            "message_arrow_4": "",
            "message_arrow_5": ""
        },
        {
            "id": "39",
            "refresh_room_id": "127",
            "idol_disp_1": "",
            "idol_disp_2": "",
            "idol_disp_3": "",
            "idol_disp_4": "",
            "idol_disp_5": "",
            "motion1": "",
            "motion2": "",
            "motion3": "smile_left",
            "motion4": "",
            "motion5": "",
            "bg_image": "",
            "message": "なにか方法はないでしょうか～？\n小春もサンタさんに会って、\nありがとうって伝えたいです～。",
            "message_window_type": "",
            "message_arrow_1": "",
            "message_arrow_2": "",
            "message_arrow_3": "1",
            "message_arrow_4": "",
            "message_arrow_5": ""
        },
        {
            "id": "40",
            "refresh_room_id": "127",
            "idol_disp_1": "",
            "idol_disp_2": "",
            "idol_disp_3": "",
            "idol_disp_4": "",
            "idol_disp_5": "",
            "motion1": "",
            "motion2": "",
            "motion3": "",
            "motion4": "nod",
            "motion5": "",
            "bg_image": "",
            "message": "………………。\n探して、捕まえる……。\nぎゅって……する。",
            "message_window_type": "",
            "message_arrow_1": "",
            "message_arrow_2": "",
            "message_arrow_3": "",
            "message_arrow_4": "1",
            "message_arrow_5": ""
        },
        {
            "id": "41",
            "refresh_room_id": "127",
            "idol_disp_1": "",
            "idol_disp_2": "",
            "idol_disp_3": "",
            "idol_disp_4": "",
            "idol_disp_5": "",
            "motion1": "",
            "motion2": "smile_right",
            "motion3": "",
            "motion4": "",
            "motion5": "",
            "bg_image": "",
            "message": "まぁ、そうですわね！\nまだ、近くにいらっしゃるかも\nしれません。探してみましょう！",
            "message_window_type": "",
            "message_arrow_1": "",
            "message_arrow_2": "1",
            "message_arrow_3": "",
            "message_arrow_4": "",
            "message_arrow_5": ""
        },
        {
            "id": "42",
            "refresh_room_id": "127",
            "idol_disp_1": "",
            "idol_disp_2": "",
            "idol_disp_3": "",
            "idol_disp_4": "",
            "idol_disp_5": "",
            "motion1": "",
            "motion2": "",
            "motion3": "trouble",
            "motion4": "",
            "motion5": "",
            "bg_image": "",
            "message": "でも見つけられるでしょうか～。\nとーっても速いトナカイさんに\n乗ってるかもしれませんし～…。",
            "message_window_type": "",
            "message_arrow_1": "",
            "message_arrow_2": "",
            "message_arrow_3": "1",
            "message_arrow_4": "",
            "message_arrow_5": ""
        },
        {
            "id": "43",
            "refresh_room_id": "127",
            "idol_disp_1": "",
            "idol_disp_2": "",
            "idol_disp_3": "",
            "idol_disp_4": "",
            "idol_disp_5": "",
            "motion1": "",
            "motion2": "",
            "motion3": "",
            "motion4": "trouble",
            "motion5": "",
            "bg_image": "",
            "message": "それに……サンタも……\n足……速い、かも……？\n……どうしよう。",
            "message_window_type": "",
            "message_arrow_1": "",
            "message_arrow_2": "",
            "message_arrow_3": "",
            "message_arrow_4": "1",
            "message_arrow_5": ""
        },
        {
            "id": "44",
            "refresh_room_id": "127",
            "idol_disp_1": "",
            "idol_disp_2": "",
            "idol_disp_3": "",
            "idol_disp_4": "",
            "idol_disp_5": "",
            "motion1": "joy",
            "motion2": "",
            "motion3": "",
            "motion4": "",
            "motion5": "",
            "bg_image": "",
            "message": "みんな……\nみゆき、わかったよ！",
            "message_window_type": "",
            "message_arrow_1": "1",
            "message_arrow_2": "",
            "message_arrow_3": "",
            "message_arrow_4": "",
            "message_arrow_5": ""
        },
        {
            "id": "45",
            "refresh_room_id": "127",
            "idol_disp_1": "",
            "idol_disp_2": "",
            "idol_disp_3": "",
            "idol_disp_4": "",
            "idol_disp_5": "",
            "motion1": "",
            "motion2": "notice",
            "motion3": "",
            "motion4": "",
            "motion5": "",
            "bg_image": "",
            "message": "まぁ！　サンタさんの居場所が\nわかりましたの？",
            "message_window_type": "",
            "message_arrow_1": "",
            "message_arrow_2": "1",
            "message_arrow_3": "",
            "message_arrow_4": "",
            "message_arrow_5": ""
        },
        {
            "id": "46",
            "refresh_room_id": "127",
            "idol_disp_1": "",
            "idol_disp_2": "",
            "idol_disp_3": "",
            "idol_disp_4": "",
            "idol_disp_5": "",
            "motion1": "smile_right",
            "motion2": "",
            "motion3": "",
            "motion4": "",
            "motion5": "",
            "bg_image": "",
            "message": "うん。前に都ちゃんが言ってたの。\n『犯人は、必ず現場に戻ってくる』\nって！",
            "message_window_type": "",
            "message_arrow_1": "1",
            "message_arrow_2": "",
            "message_arrow_3": "",
            "message_arrow_4": "",
            "message_arrow_5": ""
        },
        {
            "id": "47",
            "refresh_room_id": "127",
            "idol_disp_1": "",
            "idol_disp_2": "",
            "idol_disp_3": "",
            "idol_disp_4": "",
            "idol_disp_5": "",
            "motion1": "",
            "motion2": "",
            "motion3": "",
            "motion4": "smile_left",
            "motion5": "",
            "bg_image": "",
            "message": "サンタ……戻ってきたとき……\n捕まえる……？",
            "message_window_type": "",
            "message_arrow_1": "",
            "message_arrow_2": "",
            "message_arrow_3": "",
            "message_arrow_4": "1",
            "message_arrow_5": ""
        },
        {
            "id": "48",
            "refresh_room_id": "127",
            "idol_disp_1": "",
            "idol_disp_2": "",
            "idol_disp_3": "",
            "idol_disp_4": "",
            "idol_disp_5": "",
            "motion1": "",
            "motion2": "",
            "motion3": "nod",
            "motion4": "",
            "motion5": "",
            "bg_image": "",
            "message": "小春たちがいても、\n姿を現してくれるでしょうか～？",
            "message_window_type": "",
            "message_arrow_1": "",
            "message_arrow_2": "",
            "message_arrow_3": "1",
            "message_arrow_4": "",
            "message_arrow_5": ""
        },
        {
            "id": "49",
            "refresh_room_id": "127",
            "idol_disp_1": "",
            "idol_disp_2": "",
            "idol_disp_3": "",
            "idol_disp_4": "",
            "idol_disp_5": "",
            "motion1": "light_joy",
            "motion2": "",
            "motion3": "",
            "motion4": "",
            "motion5": "",
            "bg_image": "",
            "message": "んー…あっ、じゃあ！\nツリーの下に、お礼のお手紙を\n置いておくのはどうかなっ？",
            "message_window_type": "",
            "message_arrow_1": "1",
            "message_arrow_2": "",
            "message_arrow_3": "",
            "message_arrow_4": "",
            "message_arrow_5": ""
        },
        {
            "id": "50",
            "refresh_room_id": "127",
            "idol_disp_1": "",
            "idol_disp_2": "",
            "idol_disp_3": "",
            "idol_disp_4": "",
            "idol_disp_5": "",
            "motion1": "",
            "motion2": "",
            "motion3": "smile_left",
            "motion4": "",
            "motion5": "",
            "bg_image": "",
            "message": "いいですね～♪　それなら、\nサンタさんにありがとうって\n伝えられます～！",
            "message_window_type": "",
            "message_arrow_1": "",
            "message_arrow_2": "",
            "message_arrow_3": "1",
            "message_arrow_4": "",
            "message_arrow_5": ""
        },
        {
            "id": "51",
            "refresh_room_id": "127",
            "idol_disp_1": "",
            "idol_disp_2": "",
            "idol_disp_3": "",
            "idol_disp_4": "",
            "idol_disp_5": "",
            "motion1": "",
            "motion2": "joy",
            "motion3": "",
            "motion4": "",
            "motion5": "",
            "bg_image": "",
            "message": "仰るとおりですわ♪　戻ってきて、\nきちんとプレゼントが行き渡ったか\n確認なさるかもしれませんものね。",
            "message_window_type": "",
            "message_arrow_1": "",
            "message_arrow_2": "1",
            "message_arrow_3": "",
            "message_arrow_4": "",
            "message_arrow_5": ""
        },
        {
            "id": "52",
            "refresh_room_id": "127",
            "idol_disp_1": "",
            "idol_disp_2": "",
            "idol_disp_3": "",
            "idol_disp_4": "",
            "idol_disp_5": "",
            "motion1": "",
            "motion2": "",
            "motion3": "",
            "motion4": "smile_left",
            "motion5": "",
            "bg_image": "",
            "message": "他のみんなも……誘う……？\nサンタに、手紙……ありがとう……\n書いて……置いておくの……。",
            "message_window_type": "",
            "message_arrow_1": "",
            "message_arrow_2": "",
            "message_arrow_3": "",
            "message_arrow_4": "1",
            "message_arrow_5": ""
        },
        {
            "id": "53",
            "refresh_room_id": "127",
            "idol_disp_1": "",
            "idol_disp_2": "",
            "idol_disp_3": "",
            "idol_disp_4": "",
            "idol_disp_5": "",
            "motion1": "",
            "motion2": "",
            "motion3": "nod_smile",
            "motion4": "",
            "motion5": "",
            "bg_image": "",
            "message": "そうですね～♪\nサンタさんには、小春たちから\nお手紙をプレゼントしましょう～♪",
            "message_window_type": "",
            "message_arrow_1": "",
            "message_arrow_2": "",
            "message_arrow_3": "1",
            "message_arrow_4": "",
            "message_arrow_5": ""
        },
        {
            "id": "54",
            "refresh_room_id": "127",
            "idol_disp_1": "",
            "idol_disp_2": "",
            "idol_disp_3": "",
            "idol_disp_4": "",
            "idol_disp_5": "",
            "motion1": "",
            "motion2": "joy",
            "motion3": "",
            "motion4": "",
            "motion5": "",
            "bg_image": "",
            "message": "そうと決まれば、なおのこと、\n早くクリスマス会を始めましょう！\nわたくし、他の子も見たいですし♪",
            "message_window_type": "",
            "message_arrow_1": "",
            "message_arrow_2": "1",
            "message_arrow_3": "",
            "message_arrow_4": "",
            "message_arrow_5": ""
        },
        {
            "id": "55",
            "refresh_room_id": "127",
            "idol_disp_1": "",
            "idol_disp_2": "",
            "idol_disp_3": "",
            "idol_disp_4": "",
            "idol_disp_5": "",
            "motion1": "",
            "motion2": "",
            "motion3": "",
            "motion4": "nod_smile",
            "motion5": "",
            "bg_image": "",
            "message": "新しい友だち……たくさん……♪",
            "message_window_type": "",
            "message_arrow_1": "",
            "message_arrow_2": "",
            "message_arrow_3": "",
            "message_arrow_4": "1",
            "message_arrow_5": ""
        },
        {
            "id": "56",
            "refresh_room_id": "127",
            "idol_disp_1": "",
            "idol_disp_2": "",
            "idol_disp_3": "",
            "idol_disp_4": "",
            "idol_disp_5": "",
            "motion1": "light_joy",
            "motion2": "",
            "motion3": "",
            "motion4": "",
            "motion5": "",
            "bg_image": "",
            "message": "早くやろうって、言いに行こっか！\nみゆきたち、もう待てないよーって♪",
            "message_window_type": "",
            "message_arrow_1": "1",
            "message_arrow_2": "",
            "message_arrow_3": "",
            "message_arrow_4": "",
            "message_arrow_5": ""
        },
        {
            "id": "57",
            "refresh_room_id": "127",
            "idol_disp_1": "",
            "idol_disp_2": "",
            "idol_disp_3": "",
            "idol_disp_4": "",
            "idol_disp_5": "",
            "motion1": "",
            "motion2": "shout",
            "motion3": "",
            "motion4": "",
            "motion5": "",
            "bg_image": "",
            "message": "ええ！　では改めて……\n今日は存分に楽しみましょうね、\nみなさん♪",
            "message_window_type": "",
            "message_arrow_1": "",
            "message_arrow_2": "1",
            "message_arrow_3": "",
            "message_arrow_4": "",
            "message_arrow_5": ""
        },
        {
            "id": "58",
            "refresh_room_id": "127",
            "idol_disp_1": "",
            "idol_disp_2": "",
            "idol_disp_3": "",
            "idol_disp_4": "",
            "idol_disp_5": "",
            "motion1": "joy",
            "motion2": "",
            "motion3": "joy",
            "motion4": "joy",
            "motion5": "",
            "bg_image": "",
            "message": "はーい♪",
            "message_window_type": "",
            "message_arrow_1": "1",
            "message_arrow_2": "",
            "message_arrow_3": "1",
            "message_arrow_4": "1",
            "message_arrow_5": ""
        }
    ],
    "bg_list": {
        "6": "../../idolmaster/image_sp/ui/refresh_room/bg/bg6.jpg",
        "": "../../idolmaster/image_sp/ui/refresh_room/bg/bg.jpg"
    },
    "is_multiply": false,
    "dummy_img": "../../idolmaster/image_sp/ui/refresh_room/name_plate/__DUMMY__.png",
    "dialogue_swf": "../../idolmaster/refresh_room/petit_refresh_room_balloon_swf",
    "default_swf": "../../idolmaster/refresh_room/petit_refresh_room_character_swf"
}